{"data":{"openWeather":{"city":{"name":"Tyler"},"list":[{"weather":[{"description":"overcast clouds","icon":"04n"}],"main":{"temp":80.83,"pressure":1012.19,"humidity":69,"temp_min":80.83,"temp_max":82.49},"wind":{"deg":0.182,"speed":7.76},"dt_txt":"2019-08-28 00:00:00"},{"weather":[{"description":"overcast clouds","icon":"04n"}],"main":{"temp":75.31,"pressure":1013.9,"humidity":74,"temp_min":75.31,"temp_max":76.55},"wind":{"deg":26.375,"speed":5.75},"dt_txt":"2019-08-28 03:00:00"},{"weather":[{"description":"scattered clouds","icon":"03n"}],"main":{"temp":73.74,"pressure":1014.8,"humidity":77,"temp_min":73.74,"temp_max":74.57},"wind":{"deg":359.401,"speed":6.62},"dt_txt":"2019-08-28 06:00:00"},{"weather":[{"description":"scattered clouds","icon":"03n"}],"main":{"temp":72.18,"pressure":1014.52,"humidity":88,"temp_min":72.18,"temp_max":72.59},"wind":{"deg":36.01,"speed":2.17},"dt_txt":"2019-08-28 09:00:00"},{"weather":[{"description":"moderate rain","icon":"10d"}],"main":{"temp":71.87,"pressure":1016.46,"humidity":94,"temp_min":71.87,"temp_max":71.87},"wind":{"deg":54.888,"speed":2.46},"dt_txt":"2019-08-28 12:00:00"},{"weather":[{"description":"light rain","icon":"10d"}],"main":{"temp":79.25,"pressure":1017.24,"humidity":83,"temp_min":79.25,"temp_max":79.25},"wind":{"deg":37.825,"speed":6.04},"dt_txt":"2019-08-28 15:00:00"},{"weather":[{"description":"light rain","icon":"10d"}],"main":{"temp":85.76,"pressure":1016.49,"humidity":65,"temp_min":85.76,"temp_max":85.76},"wind":{"deg":28.533,"speed":4.36},"dt_txt":"2019-08-28 18:00:00"},{"weather":[{"description":"light rain","icon":"10d"}],"main":{"temp":87.83,"pressure":1014.63,"humidity":58,"temp_min":87.83,"temp_max":87.83},"wind":{"deg":38.342,"speed":9.57},"dt_txt":"2019-08-28 21:00:00"},{"weather":[{"description":"broken clouds","icon":"04n"}],"main":{"temp":86.4,"pressure":1013.83,"humidity":61,"temp_min":86.4,"temp_max":86.4},"wind":{"deg":46.724,"speed":7.16},"dt_txt":"2019-08-29 00:00:00"},{"weather":[{"description":"clear sky","icon":"01n"}],"main":{"temp":77.96,"pressure":1015.79,"humidity":77,"temp_min":77.96,"temp_max":77.96},"wind":{"deg":80.857,"speed":8.3},"dt_txt":"2019-08-29 03:00:00"},{"weather":[{"description":"clear sky","icon":"01n"}],"main":{"temp":74.57,"pressure":1016.21,"humidity":86,"temp_min":74.57,"temp_max":74.57},"wind":{"deg":95.105,"speed":6.62},"dt_txt":"2019-08-29 06:00:00"},{"weather":[{"description":"clear sky","icon":"01n"}],"main":{"temp":72.05,"pressure":1015.73,"humidity":95,"temp_min":72.05,"temp_max":72.05},"wind":{"deg":91.859,"speed":6.62},"dt_txt":"2019-08-29 09:00:00"},{"weather":[{"description":"clear sky","icon":"01d"}],"main":{"temp":70.91,"pressure":1016.42,"humidity":96,"temp_min":70.91,"temp_max":70.91},"wind":{"deg":96.508,"speed":6.42},"dt_txt":"2019-08-29 12:00:00"},{"weather":[{"description":"clear sky","icon":"01d"}],"main":{"temp":81.56,"pressure":1017.4,"humidity":71,"temp_min":81.56,"temp_max":81.56},"wind":{"deg":113.401,"speed":8.57},"dt_txt":"2019-08-29 15:00:00"},{"weather":[{"description":"clear sky","icon":"01d"}],"main":{"temp":90.06,"pressure":1015.77,"humidity":53,"temp_min":90.06,"temp_max":90.06},"wind":{"deg":100.477,"speed":7.07},"dt_txt":"2019-08-29 18:00:00"},{"weather":[{"description":"light rain","icon":"10d"}],"main":{"temp":90.23,"pressure":1013.77,"humidity":54,"temp_min":90.23,"temp_max":90.23},"wind":{"deg":122.811,"speed":11.63},"dt_txt":"2019-08-29 21:00:00"},{"weather":[{"description":"light rain","icon":"10n"}],"main":{"temp":88.38,"pressure":1013.52,"humidity":59,"temp_min":88.38,"temp_max":88.38},"wind":{"deg":107.608,"speed":7.4},"dt_txt":"2019-08-30 00:00:00"},{"weather":[{"description":"few clouds","icon":"02n"}],"main":{"temp":79.61,"pressure":1015.14,"humidity":73,"temp_min":79.61,"temp_max":79.61},"wind":{"deg":120.022,"speed":8.25},"dt_txt":"2019-08-30 03:00:00"},{"weather":[{"description":"few clouds","icon":"02n"}],"main":{"temp":77.11,"pressure":1015.41,"humidity":75,"temp_min":77.11,"temp_max":77.11},"wind":{"deg":116.829,"speed":7.83},"dt_txt":"2019-08-30 06:00:00"},{"weather":[{"description":"few clouds","icon":"02n"}],"main":{"temp":74.45,"pressure":1015.51,"humidity":86,"temp_min":74.45,"temp_max":74.45},"wind":{"deg":133.005,"speed":7.67},"dt_txt":"2019-08-30 09:00:00"},{"weather":[{"description":"clear sky","icon":"01d"}],"main":{"temp":72.77,"pressure":1016.24,"humidity":92,"temp_min":72.77,"temp_max":72.77},"wind":{"deg":137.348,"speed":6.69},"dt_txt":"2019-08-30 12:00:00"},{"weather":[{"description":"light rain","icon":"10d"}],"main":{"temp":83.33,"pressure":1017.31,"humidity":68,"temp_min":83.33,"temp_max":83.33},"wind":{"deg":152.559,"speed":6.6},"dt_txt":"2019-08-30 15:00:00"},{"weather":[{"description":"light rain","icon":"10d"}],"main":{"temp":91.26,"pressure":1016.35,"humidity":49,"temp_min":91.26,"temp_max":91.26},"wind":{"deg":119.38,"speed":7.58},"dt_txt":"2019-08-30 18:00:00"},{"weather":[{"description":"light rain","icon":"10d"}],"main":{"temp":85.55,"pressure":1014.26,"humidity":63,"temp_min":85.55,"temp_max":85.55},"wind":{"deg":187.664,"speed":6.11},"dt_txt":"2019-08-30 21:00:00"},{"weather":[{"description":"light rain","icon":"10n"}],"main":{"temp":86.31,"pressure":1014.04,"humidity":62,"temp_min":86.31,"temp_max":86.31},"wind":{"deg":108.835,"speed":7.61},"dt_txt":"2019-08-31 00:00:00"},{"weather":[{"description":"clear sky","icon":"01n"}],"main":{"temp":78.38,"pressure":1015.6,"humidity":73,"temp_min":78.38,"temp_max":78.38},"wind":{"deg":132.445,"speed":7.81},"dt_txt":"2019-08-31 03:00:00"},{"weather":[{"description":"few clouds","icon":"02n"}],"main":{"temp":75.83,"pressure":1016.22,"humidity":78,"temp_min":75.83,"temp_max":75.83},"wind":{"deg":128.775,"speed":8.37},"dt_txt":"2019-08-31 06:00:00"},{"weather":[{"description":"clear sky","icon":"01n"}],"main":{"temp":72.23,"pressure":1016.07,"humidity":88,"temp_min":72.23,"temp_max":72.23},"wind":{"deg":114.625,"speed":7.54},"dt_txt":"2019-08-31 09:00:00"},{"weather":[{"description":"clear sky","icon":"01d"}],"main":{"temp":70.56,"pressure":1016.89,"humidity":91,"temp_min":70.56,"temp_max":70.56},"wind":{"deg":116.181,"speed":6.26},"dt_txt":"2019-08-31 12:00:00"},{"weather":[{"description":"light rain","icon":"10d"}],"main":{"temp":79.79,"pressure":1017.98,"humidity":71,"temp_min":79.79,"temp_max":79.79},"wind":{"deg":113.792,"speed":8.99},"dt_txt":"2019-08-31 15:00:00"},{"weather":[{"description":"light rain","icon":"10d"}],"main":{"temp":88.09,"pressure":1016.84,"humidity":51,"temp_min":88.09,"temp_max":88.09},"wind":{"deg":127.566,"speed":6.44},"dt_txt":"2019-08-31 18:00:00"},{"weather":[{"description":"light rain","icon":"10d"}],"main":{"temp":87.89,"pressure":1014.4,"humidity":51,"temp_min":87.89,"temp_max":87.89},"wind":{"deg":140.693,"speed":4.03},"dt_txt":"2019-08-31 21:00:00"},{"weather":[{"description":"light rain","icon":"10n"}],"main":{"temp":86.27,"pressure":1014,"humidity":56,"temp_min":86.27,"temp_max":86.27},"wind":{"deg":44.573,"speed":3.83},"dt_txt":"2019-09-01 00:00:00"},{"weather":[{"description":"few clouds","icon":"02n"}],"main":{"temp":77.61,"pressure":1015.47,"humidity":59,"temp_min":77.61,"temp_max":77.61},"wind":{"deg":109.816,"speed":4},"dt_txt":"2019-09-01 03:00:00"},{"weather":[{"description":"few clouds","icon":"02n"}],"main":{"temp":74.03,"pressure":1016.31,"humidity":53,"temp_min":74.03,"temp_max":74.03},"wind":{"deg":97.553,"speed":7.07},"dt_txt":"2019-09-01 06:00:00"},{"weather":[{"description":"scattered clouds","icon":"03n"}],"main":{"temp":70.43,"pressure":1016.2,"humidity":66,"temp_min":70.43,"temp_max":70.43},"wind":{"deg":124.568,"speed":7.09},"dt_txt":"2019-09-01 09:00:00"},{"weather":[{"description":"few clouds","icon":"02d"}],"main":{"temp":68.76,"pressure":1017.41,"humidity":75,"temp_min":68.76,"temp_max":68.76},"wind":{"deg":116.051,"speed":5.68},"dt_txt":"2019-09-01 12:00:00"},{"weather":[{"description":"clear sky","icon":"01d"}],"main":{"temp":80.51,"pressure":1018.29,"humidity":56,"temp_min":80.51,"temp_max":80.51},"wind":{"deg":111.528,"speed":6.78},"dt_txt":"2019-09-01 15:00:00"},{"weather":[{"description":"clear sky","icon":"01d"}],"main":{"temp":88.97,"pressure":1017.49,"humidity":37,"temp_min":88.97,"temp_max":88.97},"wind":{"deg":78.495,"speed":6.96},"dt_txt":"2019-09-01 18:00:00"},{"weather":[{"description":"clear sky","icon":"01d"}],"main":{"temp":92.1,"pressure":1014.85,"humidity":30,"temp_min":92.1,"temp_max":92.1},"wind":{"deg":65.971,"speed":7.85},"dt_txt":"2019-09-01 21:00:00"}]}}}